{
  "games": [
    {
      "turns": [
        {
          "state": {
            "p1": {
              "pos": 1,
              "energy": 30000
            },
            "p2": {
              "pos": 8,
              "energy": 30000
            }
          },
          "moves": {
            "p1": {
              "kind": "Forward",
              "energy_spent": 950
            },
            "p2": {
              "kind": "Forward",
              "energy_spent": 950
            }
          }
        },
        {
          "state": {
            "p1": {
              "pos": 2,
              "energy": 29050
            },
            "p2": {
              "pos": 7,
              "energy": 29050
            }
          },
          "moves": {
            "p1": {
              "kind": "Stand",
              "energy_spent": 2445
            },
            "p2": {
              "kind": "Lunge",
              "energy_spent": 4873
            }
          }
        },
        {
          "state": {
            "p1": {
              "pos": 2,
              "energy": 26605
            },
            "p2": {
              "pos": 5,
              "energy": 24177
            }
          },
          "moves": {
            "p1": {
              "kind": "Stand",
              "energy_spent": 3007
            },
            "p2": {
              "kind": "Forward",
              "energy_spent": 2445
            }
          }
        },
        {
          "state": {
            "p1": {
              "pos": 2,
              "energy": 23598
            },
            "p2": {
              "pos": 4,
              "energy": 21732
            }
          },
          "moves": {
            "p1": {
              "kind": "Stand",
              "energy_spent": 3007
            },
            "p2": {
              "kind": "Lunge",
              "energy_spent": 2448
            }
          }
        }
      ],
      "end": {
        "P2Victory": {
          "p1": {
            "pos": 2,
            "energy": 20591
          },
          "p2": {
            "pos": 2,
            "energy": 19284
          }
        }
      }
    }
  ]
}
